tensionflow/__init__.py
tensionflow/cli.py
tensionflow/datasets/__init__.py
tensionflow/datasets/fma.py
tensionflow/datasets/nsynth.py
tensionflow/feature.py
tensionflow/models/__init__.py
tensionflow/models/base.py
tensionflow/models/convpoolmodel.py
tensionflow/processing.py
tensionflow/util/__init__.py
tensionflow/util/cli_util.py
tensionflow-0.1.2.dist-info/entry_points.txt
tensionflow-0.1.2.dist-info/LICENSE
tensionflow-0.1.2.dist-info/WHEEL
tensionflow-0.1.2.dist-info/METADATA
tensionflow-0.1.2.dist-info/RECORD
